{
  "id": "I-012b",
  "year": 2026,
  "category": "I. 수시 모집 지원 현황",
  "subcategory": "",
  "title": "지원율 하락 5개 모집단위(정원외)",
  "subtitle": null,
  "headers": ["순위", "모집단위", "2026", "2025", "증감"],
  "rows": [
    ["1", "전기전자융합학부", "4.27", "5.55", "-1.27"],
    ["2", "미래모빌리티공학부", "5.81", "6.56", "-0.75"],
    ["3", "공공인재학부", "3.80", "4.47", "-0.67"],
    ["4", "경영경제융합학부", "4.88", "4.84", "+0.04"],
    ["5", "스포츠과학부", "4.60", "4.50", "+0.10"]
  ],
  "totals": null,
  "chart_hint": "bar_simple",
  "meta": {
    "source_file": "2026학년도 수시모집 통계작업.hwpx",
    "table_index": 12,
    "row_count": 5,
    "col_count": 5,
    "caption": "지원율 하락 5개 모집단위(정원외)",
    "updated_at": "2026-05-06",
    "status": "auto-extracted",
    "note": "T012(정원 외)에서 하락 5개 컬럼만 분리. 4·5위는 원본도 +0.04/+0.10이지만 '하락' 목록에 포함되어 있어 원본 그대로 유지."
  }
}
