{
  "id": "II-052",
  "year": 2026,
  "category": "II. 대학별 고사(면접·실기) 결시율 현황",
  "subcategory": "",
  "title": "모집단위2026학년도2025학년도증감면접 대상자결시자결시율(%)면접 대상자결시자결시율(%)스포츠과학부 농구(남, 가드)635030050농구(남, 센터)2002000농구(남, 포워드)9222.228112.59.72농구",
  "subtitle": null,
  "headers": [
    "",
    "최초합격자 현황",
    "최초합격자 현황"
  ],
  "rows": [],
  "totals": null,
  "chart_hint": "bar_simple",
  "meta": {
    "source_file": "2026학년도 수시모집 통계작업.hwpx",
    "table_index": 52,
    "row_count": 3,
    "col_count": 3,
    "caption": "모집단위2026학년도2025학년도증감면접 대상자결시자결시율(%)면접 대상자결시자결시율(%)스포츠과학부 농구(남, 가드)635030050농구(남, 센터)2002000농구(남, 포워드)9222.228112.59.72농구(여, 가드)1002150-50농구(여, 센터)2001000농구(여, 포워드)4003000볼링(여)2002000복싱(남, 60kg이하)1000000복싱(남, 75kg이하)1000000수영(경영)1022060020양궁(남)2001000양궁(여)0001000펜싱(여, 에뻬)0001000계40717.53026.6710.83",
    "header_rows_detected": 3,
    "updated_at": "2026-05-06",
    "status": "auto-extracted",
    "note": "hwpx_to_json.py 자동 변환. 헤더 행 수는 자동 감지(숫자 비율 기반). 오감지 가능성 있음."
  }
}